ml_modeler_24sea/__init__.py
ml_modeler_24sea/config.py
ml_modeler_24sea/constants.py
ml_modeler_24sea/version.py
ml_modeler_24sea/misc/__init__.py
ml_modeler_24sea/misc/preprocessors.py
ml_modeler_24sea/misc/utils.py
ml_modeler_24sea/tasks/__init__.py
ml_modeler_24sea/tasks/ingest.py
ml_modeler_24sea/tasks/optimize.py
ml_modeler_24sea/tasks/split.py
ml_modeler_24sea/tasks/train.py
ml_modeler_24sea/tasks/transform.py
ml_modeler_24sea-0.1.1.dist-info/licenses/LICENSE
ml_modeler_24sea-0.1.1.dist-info/WHEEL
ml_modeler_24sea-0.1.1.dist-info/METADATA
ml_modeler_24sea-0.1.1.dist-info/RECORD
